langinsight_langchain/__init__.py
langinsight_langchain/callback_handler.py
langinsight_langchain/client/.gitignore
langinsight_langchain/client/README.md
langinsight_langchain/client/langinsight_client/__init__.py
langinsight_langchain/client/langinsight_client/api/__init__.py
langinsight_langchain/client/langinsight_client/api/default/__init__.py
langinsight_langchain/client/langinsight_client/api/default/get_clients.py
langinsight_langchain/client/langinsight_client/api/default/get_projects.py
langinsight_langchain/client/langinsight_client/api/default/post_clients.py
langinsight_langchain/client/langinsight_client/api/default/post_projects.py
langinsight_langchain/client/langinsight_client/api/default/post_traces.py
langinsight_langchain/client/langinsight_client/client.py
langinsight_langchain/client/langinsight_client/errors.py
langinsight_langchain/client/langinsight_client/models/__init__.py
langinsight_langchain/client/langinsight_client/models/get_clients_response_200_item.py
langinsight_langchain/client/langinsight_client/models/get_projects_response_200_item.py
langinsight_langchain/client/langinsight_client/models/get_projects_response_200_item_client.py
langinsight_langchain/client/langinsight_client/models/post_clients_body.py
langinsight_langchain/client/langinsight_client/models/post_clients_response_201.py
langinsight_langchain/client/langinsight_client/models/post_projects_body.py
langinsight_langchain/client/langinsight_client/models/post_projects_response_201.py
langinsight_langchain/client/langinsight_client/models/post_projects_response_201_client.py
langinsight_langchain/client/langinsight_client/models/post_traces_body.py
langinsight_langchain/client/langinsight_client/models/post_traces_response_201.py
langinsight_langchain/client/langinsight_client/py.typed
langinsight_langchain/client/langinsight_client/types.py
langinsight_langchain/client/pyproject.toml
langinsight_langchain-0.0.1.dist-info/METADATA
langinsight_langchain-0.0.1.dist-info/WHEEL
langinsight_langchain-0.0.1.dist-info/RECORD
