Metadata-Version: 2.4
Name: langinsight-langchain
Version: 0.0.1
Summary: LangInsight callback handler for LangChain - Monitor and trace your LangChain LLM applications
Author: iZ.inc
Requires-Python: >=3.10.0,<4.0
Classifier: Programming Language :: Python :: 3
Classifier: Programming Language :: Python :: 3.10
Classifier: Programming Language :: Python :: 3.11
Classifier: Programming Language :: Python :: 3.12
Classifier: Programming Language :: Python :: 3.13
Classifier: Programming Language :: Python :: 3.14
Requires-Dist: langchain-core (>=1.0.0,<2.0.0)
